LICENSE
README.md
setup.py
print/__init__.py
print/helloworld.py
print_0_world.egg-info/PKG-INFO
print_0_world.egg-info/SOURCES.txt
print_0_world.egg-info/dependency_links.txt
print_0_world.egg-info/top_level.txt
tests/__init__.py
tests/print/__init__.py
tests/print/helloworldtest.py