Metadata-Version: 2.1
Name: print-0-world
Version: 0.1.0
Summary: description of my package
Home-page: UNKNOWN
Author: Aman
Author-email: aman.email@example.com
License: UNKNOWN
Platform: UNKNOWN
Classifier: Programming Language :: Python :: 3
Classifier: License :: OSI Approved :: MIT License
Classifier: Operating System :: OS Independent
Requires-Python: >=3.6
License-File: LICENSE
